dbhose_airflow/LOGO
dbhose_airflow/__init__.py
dbhose_airflow/airflow_connect.py
dbhose_airflow/chunk_query.py
dbhose_airflow/dq_check.py
dbhose_airflow/dumper.py
dbhose_airflow/move_method.py
dbhose_airflow/ddl/clickhouse.sql
dbhose_airflow/ddl/greenplum.sql
dbhose_airflow/ddl/postgres.sql
dbhose_airflow/dq/clickhouse/empty.sql
dbhose_airflow/dq/clickhouse/future.sql
dbhose_airflow/dq/clickhouse/infinity.sql
dbhose_airflow/dq/clickhouse/nan.sql
dbhose_airflow/dq/clickhouse/sum.sql
dbhose_airflow/dq/clickhouse/total.sql
dbhose_airflow/dq/clickhouse/uniq.sql
dbhose_airflow/dq/greenplum/empty.sql
dbhose_airflow/dq/greenplum/future.sql
dbhose_airflow/dq/greenplum/infinity.sql
dbhose_airflow/dq/greenplum/nan.sql
dbhose_airflow/dq/greenplum/sum.sql
dbhose_airflow/dq/greenplum/total.sql
dbhose_airflow/dq/greenplum/uniq.sql
dbhose_airflow/dq/postgres/empty.sql
dbhose_airflow/dq/postgres/future.sql
dbhose_airflow/dq/postgres/infinity.sql
dbhose_airflow/dq/postgres/nan.sql
dbhose_airflow/dq/postgres/sum.sql
dbhose_airflow/dq/postgres/total.sql
dbhose_airflow/dq/postgres/uniq.sql
dbhose_airflow/move/clickhouse/delete.sql
dbhose_airflow/move/clickhouse/replace.sql
dbhose_airflow/move/greenplum/delete.sql
dbhose_airflow/move/greenplum/replace.sql
dbhose_airflow/move/postgres/delete.sql
dbhose_airflow/move/postgres/replace.sql
dbhose_airflow-0.1.0.5.dist-info/licenses/CHANGELOG.md
dbhose_airflow-0.1.0.5.dist-info/licenses/README.md
dbhose_airflow-0.1.0.5.dist-info/METADATA
dbhose_airflow-0.1.0.5.dist-info/WHEEL
dbhose_airflow-0.1.0.5.dist-info/top_level.txt
dbhose_airflow-0.1.0.5.dist-info/RECORD
