Metadata-Version: 2.4
Name: dbhose_airflow
Version: 0.1.0.5
Summary: airflow class for exchanging data between DBMSs in native binary formats.
Home-page: https://github.com/0xMihalich/dbhose_airflow
Author: 0xMihalich
Author-email: bayanmobile87@gmail.com
Project-URL: Homepage, https://github.com/0xMihalich/dbhose_airflow
Project-URL: Documentation, https://0xmihalich.github.io/dbhose_airflow/
Keywords: airflow,database,etl,clickhouse,postgresql,greenplum
Classifier: Development Status :: 4 - Beta
Classifier: Intended Audience :: Developers
Classifier: Topic :: Software Development :: Libraries :: Python Modules
Classifier: Topic :: Database
Classifier: License :: OSI Approved :: MIT License
Classifier: Programming Language :: Python :: 3.10
Classifier: Programming Language :: Python :: 3.11
Classifier: Programming Language :: Python :: 3.12
Classifier: Programming Language :: Python :: 3.13
Classifier: Programming Language :: Python :: 3.14
Classifier: Framework :: Apache Airflow
Classifier: Operating System :: OS Independent
Requires-Python: >=3.10
License-File: README.md
License-File: CHANGELOG.md
Requires-Dist: apache-airflow>=2.4.3
Requires-Dist: native-dumper==0.3.5.2
Requires-Dist: pgpack-dumper==0.3.5.2
Requires-Dist: dbhose-utils==0.0.2.5
Dynamic: author
Dynamic: author-email
Dynamic: classifier
Dynamic: description
Dynamic: description-content-type
Dynamic: home-page
Dynamic: keywords
Dynamic: license-file
Dynamic: project-url
Dynamic: requires-dist
Dynamic: requires-python
Dynamic: summary
